etfba/__init__.py
etfba/core/__init__.py
etfba/core/metabolite.py
etfba/core/model.py
etfba/core/reaction.py
etfba/io/__init__.py
etfba/io/io.py
etfba/io/results.py
etfba/optim/__init__.py
etfba/optim/optim.py
etfba/optim/variability.py
etfba-0.2.0.dist-info/LICENSE
etfba-0.2.0.dist-info/METADATA
etfba-0.2.0.dist-info/WHEEL
etfba-0.2.0.dist-info/top_level.txt
etfba-0.2.0.dist-info/RECORD
